{"timestamp": "2025-10-17T08:09:55.739057Z", "level": "ERROR", "service": "auth-service", "host": "auth-server-02", "request_id": "req-c31b5aa9", "message": "Service unavailable", "duration_ms": 5361, "status_code": 503, "user_id": null, "amount": null, "error": "ServiceUnavailable", "region": "ap-south-1", "trace_id": "trace-81cd81598d787fee", "auth_method": null, "provider": null, "session_duration": null, "currency": null, "payment_method": null, "retry_count": 1, "file_size_bytes": null, "content_type": null, "memory_percent": null, "available_mb": null, "disk_usage_percent": null, "available_gb": null, "query_params": null, "result_count": null, "recipient": null, "smtp_code": null, "metrics_count": null, "time_window": null, "product_id": null, "rating": null, "version": null, "status": null, "test": null, "validation_errors": null}
{"timestamp": "2025-10-17T08:09:55.739381Z", "level": "INFO", "service": "auth-service", "host": "auth-server-01", "request_id": "req-7f10db76", "message": "GET /api/v1/users/profile", "duration_ms": 386, "status_code": 201, "user_id": null, "amount": null, "error": null, "region": "ap-south-1", "trace_id": null, "auth_method": null, "provider": null, "session_duration": null, "currency": null, "payment_method": null, "retry_count": null, "file_size_bytes": null, "content_type": null, "memory_percent": null, "available_mb": null, "disk_usage_percent": null, "available_gb": null, "query_params": null, "result_count": null, "recipient": null, "smtp_code": null, "metrics_count": null, "time_window": null, "product_id": null, "rating": null, "version": null, "status": null, "test": null, "validation_errors": null}
{"timestamp": "2025-10-17T08:09:55.739405Z", "level": "INFO", "service": "payment-service", "host": "payment-server-02", "request_id": "req-0bd612e0", "message": "DELETE /api/v1/cart/items", "duration_ms": 495, "status_code": 201, "user_id": "user-76736", "amount": 75.0, "error": null, "region": "eu-central-1", "trace_id": null, "auth_method": null, "provider": null, "session_duration": null, "currency": "EUR", "payment_method": "paypal", "retry_count": null, "file_size_bytes": null, "content_type": null, "memory_percent": null, "available_mb": null, "disk_usage_percent": null, "available_gb": null, "query_params": null, "result_count": null, "recipient": null, "smtp_code": null, "metrics_count": null, "time_window": null, "product_id": null, "rating": null, "version": null, "status": null, "test": true, "validation_errors": null}
{"timestamp": "2025-10-17T08:09:55.739431Z", "level": "WARN", "service": "inventory-service", "host": "inventory-server-02", "request_id": "req-faabdb9f", "message": "Disk space running low", "duration_ms": null, "status_code": 200, "user_id": null, "amount": null, "error": null, "region": "eu-central-1", "trace_id": "trace-705b3782df432b00", "auth_method": null, "provider": null, "session_duration": null, "currency": null, "payment_method": null, "retry_count": null, "file_size_bytes": null, "content_type": null, "memory_percent": null, "available_mb": null, "disk_usage_percent": 98, "available_gb": 32, "query_params": null, "result_count": null, "recipient": null, "smtp_code": null, "metrics_count": null, "time_window": null, "product_id": null, "rating": null, "version": null, "status": null, "test": null, "validation_errors": null}
{"timestamp": "2025-10-17T08:09:55.739454Z", "level": "WARN", "service": "search-service", "host": "search-server-01", "request_id": "req-ef41690b", "message": "Payment declined", "duration_ms": 1145, "status_code": 402, "user_id": null, "amount": null, "error": null, "region": "ap-northeast-1", "trace_id": "trace-90903dbb57eba942", "auth_method": null, "provider": null, "session_duration": null, "currency": null, "payment_method": null, "retry_count": null, "file_size_bytes": null, "content_type": null, "memory_percent": null, "available_mb": null, "disk_usage_percent": null, "available_gb": null, "query_params": {"category": "electronics", "limit": 10}, "result_count": 9, "recipient": null, "smtp_code": null, "metrics_count": null, "time_window": null, "product_id": null, "rating": null, "version": null, "status": null, "test": null, "validation_errors": null}
{"timestamp": "2025-10-17T08:09:55.739477Z", "level": "INFO", "service": "web-api", "host": "api-server-01", "request_id": "req-707fbd58", "message": "Payment processed", "duration_ms": 262, "status_code": 201, "user_id": "user-25970", "amount": null, "error": null, "region": "eu-west-1", "trace_id": "trace-731c4eb4c6535392", "auth_method": null, "provider": null, "session_duration": null, "currency": null, "payment_method": null, "retry_count": null, "file_size_bytes": null, "content_type": null, "memory_percent": null, "available_mb": null, "disk_usage_percent": null, "available_gb": null, "query_params": null, "result_count": null, "recipient": null, "smtp_code": null, "metrics_count": null, "time_window": null, "product_id": null, "rating": null, "version": "2.1", "status": null, "test": null, "validation_errors": null}
{"timestamp": "2025-10-17T08:09:55.739488Z", "level": "INFO", "service": "web-api", "host": "api-server-03", "request_id": "req-a070ecc8", "message": "Search query executed", "duration_ms": 89, "status_code": 201, "user_id": "user-38533", "amount": null, "error": null, "region": "eu-west-1", "trace_id": null, "auth_method": null, "provider": null, "session_duration": null, "currency": null, "payment_method": null, "retry_count": null, "file_size_bytes": null, "content_type": null, "memory_percent": null, "available_mb": null, "disk_usage_percent": null, "available_gb": null, "query_params": {"category": "electronics", "limit": 10}, "result_count": 2, "recipient": null, "smtp_code": null, "metrics_count": null, "time_window": null, "product_id": null, "rating": null, "version": null, "status": null, "test": null, "validation_errors": null}
{"timestamp": "2025-10-17T08:09:55.739504Z", "level": "INFO", "service": "notification-service", "host": "notif-server-01", "request_id": "req-43e5acc5", "message": "User authentication successful", "duration_ms": 397, "status_code": 204, "user_id": "user-19295", "amount": null, "error": null, "region": "us-west-2", "trace_id": "trace-81826ff52cd95be8", "auth_method": null, "provider": null, "session_duration": null, "currency": null, "payment_method": null, "retry_count": null, "file_size_bytes": null, "content_type": null, "memory_percent": null, "available_mb": null, "disk_usage_percent": null, "available_gb": null, "query_params": null, "result_count": null, "recipient": null, "smtp_code": null, "metrics_count": null, "time_window": null, "product_id": null, "rating": null, "version": null, "status": null, "test": null, "validation_errors": null}
{"timestamp": "2025-10-17T08:09:55.739518Z", "level": "WARN", "service": "search-service", "host": "search-server-02", "request_id": "req-a33b860b", "message": "Disk space running low", "duration_ms": null, "status_code": 402, "user_id": null, "amount": null, "error": null, "region": "eu-west-1", "trace_id": null, "auth_method": null, "provider": null, "session_duration": null, "currency": null, "payment_method": null, "retry_count": null, "file_size_bytes": null, "content_type": null, "memory_percent": null, "available_mb": null, "disk_usage_percent": 91, "available_gb": 44, "query_params": null, "result_count": null, "recipient": null, "smtp_code": null, "metrics_count": null, "time_window": null, "product_id": null, "rating": null, "version": null, "status": null, "test": null, "validation_errors": null}
{"timestamp": "2025-10-17T08:09:55.739527Z", "level": "INFO", "service": "web-api", "host": "api-server-03", "request_id": "req-df323e3a", "message": "GET /api/v1/products", "duration_ms": 108, "status_code": 201, "user_id": null, "amount": null, "error": null, "region": "eu-central-1", "trace_id": "trace-26989ee732cd15d5", "auth_method": null, "provider": null, "session_duration": null, "currency": null, "payment_method": null, "retry_count": null, "file_size_bytes": 6031374, "content_type": "text/csv", "memory_percent": null, "available_mb": null, "disk_usage_percent": null, "available_gb": null, "query_params": null, "result_count": null, "recipient": null, "smtp_code": null, "metrics_count": null, "time_window": null, "product_id": "prod-86659", "rating": 2, "version": null, "status": null, "test": null, "validation_errors": null}
{"timestamp": "2025-10-17T08:09:55.739602Z", "level": "INFO", "service": "payment-service", "host": "payment-server-02", "request_id": "req-fb6efd87", "message": "GET /api/v1/products", "duration_ms": 301, "status_code": 201, "user_id": "user-45862", "amount": 969.41, "error": null, "region": "ap-northeast-1", "trace_id": "trace-74f1643658547fdd", "auth_method": null, "provider": null, "session_duration": null, "currency": "EUR", "payment_method": "debit_card", "retry_count": null, "file_size_bytes": null, "content_type": null, "memory_percent": null, "available_mb": null, "disk_usage_percent": null, "available_gb": null, "query_params": null, "result_count": null, "recipient": null, "smtp_code": null, "metrics_count": null, "time_window": null, "product_id": null, "rating": null, "version": null, "status": null, "test": null, "validation_errors": null}
{"timestamp": "2025-10-17T08:09:55.739618Z", "level": "ERROR", "service": "search-service", "host": "search-server-02", "request_id": "req-b560fb48", "message": "Database connection timeout", "duration_ms": 9433, "status_code": 504, "user_id": null, "amount": null, "error": "ConnectionTimeout", "region": "eu-west-1", "trace_id": null, "auth_method": null, "provider": null, "session_duration": null, "currency": null, "payment_method": null, "retry_count": null, "file_size_bytes": null, "content_type": null, "memory_percent": null, "available_mb": null, "disk_usage_percent": null, "available_gb": null, "query_params": null, "result_count": null, "recipient": null, "smtp_code": null, "metrics_count": null, "time_window": null, "product_id": null, "rating": null, "version": "1.0", "status": null, "test": null, "validation_errors": null}
{"timestamp": "2025-10-17T08:09:55.739629Z", "level": "WARN", "service": "payment-service", "host": "payment-server-02", "request_id": "req-87427b03", "message": "Memory usage above 80%", "duration_ms": 1450, "status_code": 200, "user_id": "user-49988", "amount": 383.99, "error": null, "region": null, "trace_id": null, "auth_method": null, "provider": null, "session_duration": null, "currency": "GBP", "payment_method": "paypal", "retry_count": null, "file_size_bytes": null, "content_type": null, "memory_percent": 90.0, "available_mb": 896, "disk_usage_percent": null, "available_gb": null, "query_params": null, "result_count": null, "recipient": null, "smtp_code": null, "metrics_count": null, "time_window": null, "product_id": null, "rating": null, "version": null, "status": null, "test": null, "validation_errors": null}
{"timestamp": "2025-10-17T08:09:55.739642Z", "level": "INFO", "service": "payment-service", "host": "payment-server-01", "request_id": "req-cef22b7d", "message": "GET /api/v1/users/profile", "duration_ms": 370, "status_code": 201, "user_id": null, "amount": 686.98, "error": null, "region": "us-central-1", "trace_id": null, "auth_method": null, "provider": null, "session_duration": null, "currency": "JPY", "payment_method": "debit_card", "retry_count": null, "file_size_bytes": null, "content_type": null, "memory_percent": null, "available_mb": null, "disk_usage_percent": null, "available_gb": null, "query_params": null, "result_count": null, "recipient": null, "smtp_code": null, "metrics_count": null, "time_window": null, "product_id": null, "rating": null, "version": null, "status": null, "test": null, "validation_errors": null}
{"timestamp": "2025-10-17T08:09:55.739654Z", "level": "INFO", "service": "analytics-service", "host": "analytics-server-01", "request_id": "req-3b2317e9", "message": "Daily report generated", "duration_ms": 258, "status_code": 201, "user_id": "user-63705", "amount": null, "error": null, "region": "us-west-2", "trace_id": "trace-49d5cea116e9e5e1", "auth_method": null, "provider": null, "session_duration": null, "currency": null, "payment_method": null, "retry_count": null, "file_size_bytes": null, "content_type": null, "memory_percent": null, "available_mb": null, "disk_usage_percent": null, "available_gb": null, "query_params": null, "result_count": null, "recipient": null, "smtp_code": null, "metrics_count": null, "time_window": null, "product_id": null, "rating": null, "version": null, "status": null, "test": null, "validation_errors": null}
{"timestamp": "2025-10-17T08:09:55.739663Z", "level": "INFO", "service": "search-service", "host": "search-server-01", "request_id": "req-269035f5", "message": "Cache refreshed successfully", "duration_ms": 31, "status_code": 200, "user_id": "user-52754", "amount": null, "error": null, "region": "us-east-1", "trace_id": null, "auth_method": null, "provider": null, "session_duration": null, "currency": null, "payment_method": null, "retry_count": null, "file_size_bytes": null, "content_type": null, "memory_percent": null, "available_mb": null, "disk_usage_percent": null, "available_gb": null, "query_params": null, "result_count": null, "recipient": null, "smtp_code": null, "metrics_count": null, "time_window": null, "product_id": null, "rating": null, "version": null, "status": null, "test": null, "validation_errors": null}
{"timestamp": "2025-10-17T08:09:55.739672Z", "level": "ERROR", "service": "inventory-service", "host": "inventory-server-01", "request_id": "req-103c2125", "message": "Internal server error", "duration_ms": 2134, "status_code": 409, "user_id": null, "amount": null, "error": "NullPointerException", "region": "us-central-1", "trace_id": null, "auth_method": null, "provider": null, "session_duration": null, "currency": null, "payment_method": null, "retry_count": null, "file_size_bytes": null, "content_type": null, "memory_percent": null, "available_mb": null, "disk_usage_percent": null, "available_gb": null, "query_params": null, "result_count": null, "recipient": null, "smtp_code": null, "metrics_count": null, "time_window": null, "product_id": null, "rating": null, "version": null, "status": null, "test": null, "validation_errors": null}
{"timestamp": "2025-10-17T08:09:55.739684Z", "level": "INFO", "service": "payment-service", "host": "payment-server-02", "request_id": "req-7443d05f", "message": "Cache refreshed successfully", "duration_ms": 377, "status_code": 200, "user_id": "user-61466", "amount": null, "error": null, "region": "ap-south-1", "trace_id": null, "auth_method": null, "provider": null, "session_duration": null, "currency": null, "payment_method": null, "retry_count": null, "file_size_bytes": null, "content_type": null, "memory_percent": null, "available_mb": null, "disk_usage_percent": null, "available_gb": null, "query_params": null, "result_count": null, "recipient": null, "smtp_code": null, "metrics_count": null, "time_window": null, "product_id": null, "rating": null, "version": null, "status": "healthy", "test": null, "validation_errors": null}
{"timestamp": "2025-10-17T08:09:55.739693Z", "level": "INFO", "service": "auth-service", "host": "auth-server-01", "request_id": "req-ab0100f1", "message": "GET /api/v1/users/profile", "duration_ms": 343, "status_code": 204, "user_id": "user-28963", "amount": null, "error": null, "region": "us-east-1", "trace_id": "trace-3b2afa5c2738d14a", "auth_method": "basic", "provider": "aws", "session_duration": 7200, "currency": null, "payment_method": null, "retry_count": null, "file_size_bytes": null, "content_type": null, "memory_percent": null, "available_mb": null, "disk_usage_percent": null, "available_gb": null, "query_params": null, "result_count": null, "recipient": null, "smtp_code": null, "metrics_count": null, "time_window": null, "product_id": null, "rating": null, "version": null, "status": null, "test": null, "validation_errors": null}
{"timestamp": "2025-10-17T08:09:55.739719Z", "level": "INFO", "service": "db-service", "host": "db-server-01", "request_id": "req-53ef4009", "message": "Daily report generated", "duration_ms": 276, "status_code": 201, "user_id": null, "amount": null, "error": null, "region": "us-central-1", "trace_id": null, "auth_method": null, "provider": null, "session_duration": null, "currency": null, "payment_method": null, "retry_count": null, "file_size_bytes": null, "content_type": null, "memory_percent": null, "available_mb": null, "disk_usage_percent": null, "available_gb": null, "query_params": null, "result_count": null, "recipient": null, "smtp_code": null, "metrics_count": null, "time_window": null, "product_id": null, "rating": null, "version": null, "status": null, "test": null, "validation_errors": null}
{"timestamp": "2025-10-17T08:09:55.739736Z", "level": "ERROR", "service": "payment-service", "host": "payment-server-01", "request_id": "req-4cfc67c5", "message": "Deadlock detected in transaction", "duration_ms": 8523, "status_code": 504, "user_id": null, "amount": null, "error": "DeadlockDetected", "region": null, "trace_id": "trace-785f75c1daf94d71", "auth_method": null, "provider": null, "session_duration": null, "currency": null, "payment_method": null, "retry_count": null, "file_size_bytes": null, "content_type": null, "memory_percent": null, "available_mb": null, "disk_usage_percent": null, "available_gb": null, "query_params": null, "result_count": null, "recipient": null, "smtp_code": null, "metrics_count": null, "time_window": null, "product_id": null, "rating": null, "version": null, "status": null, "test": null, "validation_errors": null}
{"timestamp": "2025-10-17T08:09:55.739746Z", "level": "INFO", "service": "web-api", "host": "api-server-02", "request_id": "req-32d44fd5", "message": "PUT /api/v1/cart", "duration_ms": 149, "status_code": 200, "user_id": "user-21076", "amount": null, "error": null, "region": "ap-northeast-1", "trace_id": null, "auth_method": null, "provider": null, "session_duration": null, "currency": null, "payment_method": null, "retry_count": null, "file_size_bytes": null, "content_type": null, "memory_percent": null, "available_mb": null, "disk_usage_percent": null, "available_gb": null, "query_params": null, "result_count": null, "recipient": null, "smtp_code": null, "metrics_count": null, "time_window": null, "product_id": null, "rating": null, "version": "2.1", "status": null, "test": null, "validation_errors": null}
{"timestamp": "2025-10-17T08:09:55.739758Z", "level": "INFO", "service": "db-service", "host": "db-server-01", "request_id": "req-61717e11", "message": "Payment processed", "duration_ms": 130, "status_code": 204, "user_id": "user-44924", "amount": null, "error": null, "region": null, "trace_id": null, "auth_method": null, "provider": null, "session_duration": null, "currency": null, "payment_method": null, "retry_count": null, "file_size_bytes": null, "content_type": null, "memory_percent": null, "available_mb": null, "disk_usage_percent": null, "available_gb": null, "query_params": null, "result_count": null, "recipient": null, "smtp_code": null, "metrics_count": null, "time_window": null, "product_id": null, "rating": null, "version": "2.1", "status": null, "test": null, "validation_errors": null}
{"timestamp": "2025-10-17T08:09:55.739766Z", "level": "INFO", "service": "payment-service", "host": "payment-server-02", "request_id": "req-254de291", "message": "DELETE /api/v1/cart/items", "duration_ms": 272, "status_code": 200, "user_id": "user-43417", "amount": 482.91, "error": null, "region": "ap-south-1", "trace_id": null, "auth_method": null, "provider": null, "session_duration": null, "currency": "USD", "payment_method": "bank_transfer", "retry_count": null, "file_size_bytes": null, "content_type": null, "memory_percent": null, "available_mb": null, "disk_usage_percent": null, "available_gb": null, "query_params": null, "result_count": null, "recipient": null, "smtp_code": null, "metrics_count": null, "time_window": null, "product_id": null, "rating": null, "version": null, "status": null, "test": null, "validation_errors": null}
{"timestamp": "2025-10-17T08:09:55.739778Z", "level": "INFO", "service": "web-api", "host": "api-server-03", "request_id": "req-b2a03626", "message": "PUT /api/v1/cart", "duration_ms": 356, "status_code": 201, "user_id": "user-34062", "amount": null, "error": null, "region": "us-west-2", "trace_id": null, "auth_method": null, "provider": null, "session_duration": null, "currency": null, "payment_method": null, "retry_count": null, "file_size_bytes": null, "content_type": null, "memory_percent": null, "available_mb": null, "disk_usage_percent": null, "available_gb": null, "query_params": {"category": "books", "limit": 25}, "result_count": 22, "recipient": null, "smtp_code": null, "metrics_count": null, "time_window": null, "product_id": "prod-46991", "rating": 5, "version": null, "status": "healthy", "test": null, "validation_errors": null}
{"timestamp": "2025-10-17T08:09:55.739794Z", "level": "INFO", "service": "analytics-service", "host": "analytics-server-01", "request_id": "req-4daa67fb", "message": "Daily report generated", "duration_ms": 127, "status_code": 201, "user_id": "user-22168", "amount": null, "error": null, "region": "eu-central-1", "trace_id": null, "auth_method": null, "provider": null, "session_duration": null, "currency": null, "payment_method": null, "retry_count": null, "file_size_bytes": null, "content_type": null, "memory_percent": null, "available_mb": null, "disk_usage_percent": null, "available_gb": null, "query_params": null, "result_count": null, "recipient": null, "smtp_code": null, "metrics_count": null, "time_window": null, "product_id": null, "rating": null, "version": null, "status": null, "test": null, "validation_errors": null}
{"timestamp": "2025-10-17T08:09:55.739803Z", "level": "INFO", "service": "auth-service", "host": "auth-server-01", "request_id": "req-f73d6107", "message": "Request processed successfully", "duration_ms": 103, "status_code": 204, "user_id": "user-15781", "amount": null, "error": null, "region": "eu-west-1", "trace_id": "trace-112d8b8f891559c1", "auth_method": "api_key", "provider": "google", "session_duration": 1800, "currency": null, "payment_method": null, "retry_count": null, "file_size_bytes": null, "content_type": null, "memory_percent": null, "available_mb": null, "disk_usage_percent": null, "available_gb": null, "query_params": null, "result_count": null, "recipient": null, "smtp_code": null, "metrics_count": null, "time_window": null, "product_id": null, "rating": null, "version": null, "status": null, "test": null, "validation_errors": null}
{"timestamp": "2025-10-17T08:09:55.739813Z", "level": "INFO", "service": "analytics-service", "host": "analytics-server-01", "request_id": "req-196dfca1", "message": "DELETE /api/v1/cart/items", "duration_ms": 197, "status_code": 204, "user_id": "user-27205", "amount": null, "error": null, "region": "eu-west-1", "trace_id": null, "auth_method": null, "provider": null, "session_duration": null, "currency": null, "payment_method": null, "retry_count": null, "file_size_bytes": null, "content_type": null, "memory_percent": null, "available_mb": null, "disk_usage_percent": null, "available_gb": null, "query_params": null, "result_count": null, "recipient": null, "smtp_code": null, "metrics_count": null, "time_window": null, "product_id": null, "rating": null, "version": null, "status": null, "test": null, "validation_errors": null}
{"timestamp": "2025-10-17T08:09:55.739838Z", "level": "WARN", "service": "search-service", "host": "search-server-02", "request_id": "req-dcd2bba9", "message": "Connection pool nearly exhausted", "duration_ms": 1322, "status_code": 402, "user_id": null, "amount": null, "error": null, "region": "ap-northeast-1", "trace_id": "trace-995fa35023bf844d", "auth_method": null, "provider": null, "session_duration": null, "currency": null, "payment_method": null, "retry_count": null, "file_size_bytes": null, "content_type": null, "memory_percent": null, "available_mb": null, "disk_usage_percent": null, "available_gb": null, "query_params": null, "result_count": null, "recipient": null, "smtp_code": null, "metrics_count": null, "time_window": null, "product_id": null, "rating": null, "version": null, "status": null, "test": null, "validation_errors": null}
{"timestamp": "2025-10-17T08:09:55.739848Z", "level": "ERROR", "service": "search-service", "host": "search-server-01", "request_id": "req-a18870f4", "message": "Database connection timeout", "duration_ms": 6166, "status_code": 504, "user_id": null, "amount": null, "error": "ConnectionTimeout", "region": "ap-northeast-1", "trace_id": null, "auth_method": null, "provider": null, "session_duration": null, "currency": null, "payment_method": null, "retry_count": null, "file_size_bytes": null, "content_type": null, "memory_percent": null, "available_mb": null, "disk_usage_percent": null, "available_gb": null, "query_params": {"category": "electronics", "limit": 100}, "result_count": 60, "recipient": null, "smtp_code": null, "metrics_count": null, "time_window": null, "product_id": null, "rating": null, "version": null, "status": null, "test": true, "validation_errors": null}
{"timestamp": "2025-10-17T08:09:55.739864Z", "level": "INFO", "service": "inventory-service", "host": "inventory-server-02", "request_id": "req-e02c3bc3", "message": "DELETE /api/v1/cart/items", "duration_ms": 263, "status_code": 200, "user_id": "user-60895", "amount": null, "error": null, "region": "us-east-1", "trace_id": null, "auth_method": null, "provider": null, "session_duration": null, "currency": null, "payment_method": null, "retry_count": null, "file_size_bytes": null, "content_type": null, "memory_percent": null, "available_mb": null, "disk_usage_percent": null, "available_gb": null, "query_params": null, "result_count": null, "recipient": null, "smtp_code": null, "metrics_count": null, "time_window": null, "product_id": null, "rating": null, "version": null, "status": "healthy", "test": null, "validation_errors": null}
{"timestamp": "2025-10-17T08:09:55.739877Z", "level": "INFO", "service": "inventory-service", "host": "inventory-server-02", "request_id": "req-5a0a1f9f", "message": "Payment processed", "duration_ms": 265, "status_code": 201, "user_id": null, "amount": null, "error": null, "region": "ap-northeast-1", "trace_id": null, "auth_method": null, "provider": null, "session_duration": null, "currency": null, "payment_method": null, "retry_count": null, "file_size_bytes": null, "content_type": null, "memory_percent": null, "available_mb": null, "disk_usage_percent": null, "available_gb": null, "query_params": null, "result_count": null, "recipient": null, "smtp_code": null, "metrics_count": null, "time_window": null, "product_id": null, "rating": null, "version": null, "status": null, "test": null, "validation_errors": null}
{"timestamp": "2025-10-17T08:09:55.739885Z", "level": "INFO", "service": "payment-service", "host": "payment-server-01", "request_id": "req-c3438213", "message": "Session created", "duration_ms": 320, "status_code": 200, "user_id": null, "amount": 434.69, "error": null, "region": "us-east-1", "trace_id": null, "auth_method": null, "provider": null, "session_duration": null, "currency": "EUR", "payment_method": "paypal", "retry_count": null, "file_size_bytes": null, "content_type": null, "memory_percent": null, "available_mb": null, "disk_usage_percent": null, "available_gb": null, "query_params": null, "result_count": null, "recipient": null, "smtp_code": null, "metrics_count": null, "time_window": null, "product_id": null, "rating": null, "version": null, "status": null, "test": null, "validation_errors": null}
{"timestamp": "2025-10-17T08:09:55.739897Z", "level": "WARN", "service": "payment-service", "host": "payment-server-01", "request_id": "req-13a640ca", "message": "Disk space running low", "duration_ms": null, "status_code": 200, "user_id": null, "amount": 186.12, "error": null, "region": null, "trace_id": "trace-fcf3afbd8f5e7ca8", "auth_method": null, "provider": null, "session_duration": null, "currency": "JPY", "payment_method": "bank_transfer", "retry_count": null, "file_size_bytes": null, "content_type": null, "memory_percent": null, "available_mb": null, "disk_usage_percent": 90, "available_gb": 43, "query_params": null, "result_count": null, "recipient": null, "smtp_code": null, "metrics_count": null, "time_window": null, "product_id": null, "rating": null, "version": "2.0", "status": null, "test": null, "validation_errors": null}
{"timestamp": "2025-10-17T08:09:55.739906Z", "level": "INFO", "service": "analytics-service", "host": "analytics-server-01", "request_id": "req-e09be241", "message": "Session created", "duration_ms": 121, "status_code": 201, "user_id": "user-68670", "amount": null, "error": null, "region": "us-west-2", "trace_id": null, "auth_method": null, "provider": null, "session_duration": null, "currency": null, "payment_method": null, "retry_count": null, "file_size_bytes": null, "content_type": null, "memory_percent": null, "available_mb": null, "disk_usage_percent": null, "available_gb": null, "query_params": null, "result_count": null, "recipient": null, "smtp_code": null, "metrics_count": null, "time_window": null, "product_id": null, "rating": null, "version": null, "status": null, "test": null, "validation_errors": null}
{"timestamp": "2025-10-17T08:09:55.739915Z", "level": "INFO", "service": "inventory-service", "host": "inventory-server-01", "request_id": "req-cfb63f51", "message": "User authentication successful", "duration_ms": 145, "status_code": 201, "user_id": "user-65386", "amount": null, "error": null, "region": "ap-south-1", "trace_id": null, "auth_method": null, "provider": null, "session_duration": null, "currency": null, "payment_method": null, "retry_count": null, "file_size_bytes": null, "content_type": null, "memory_percent": null, "available_mb": null, "disk_usage_percent": null, "available_gb": null, "query_params": null, "result_count": null, "recipient": null, "smtp_code": null, "metrics_count": null, "time_window": null, "product_id": null, "rating": null, "version": null, "status": null, "test": null, "validation_errors": null}
{"timestamp": "2025-10-17T08:09:55.739922Z", "level": "INFO", "service": "web-api", "host": "api-server-02", "request_id": "req-f7413ba6", "message": "Request processed successfully", "duration_ms": 473, "status_code": 204, "user_id": "user-40699", "amount": null, "error": null, "region": "eu-west-1", "trace_id": null, "auth_method": null, "provider": null, "session_duration": null, "currency": null, "payment_method": null, "retry_count": null, "file_size_bytes": null, "content_type": null, "memory_percent": null, "available_mb": null, "disk_usage_percent": null, "available_gb": null, "query_params": null, "result_count": null, "recipient": null, "smtp_code": null, "metrics_count": null, "time_window": null, "product_id": "prod-99326", "rating": 2, "version": null, "status": null, "test": null, "validation_errors": null}
{"timestamp": "2025-10-17T08:09:55.739943Z", "level": "INFO", "service": "auth-service", "host": "auth-server-02", "request_id": "req-74b16ccf", "message": "File uploaded successfully", "duration_ms": 365, "status_code": 201, "user_id": "user-92127", "amount": null, "error": null, "region": "ap-northeast-1", "trace_id": "trace-fe60ed812b3afaf0", "auth_method": "basic", "provider": "okta", "session_duration": 3600, "currency": null, "payment_method": null, "retry_count": null, "file_size_bytes": null, "content_type": null, "memory_percent": null, "available_mb": null, "disk_usage_percent": null, "available_gb": null, "query_params": null, "result_count": null, "recipient": null, "smtp_code": null, "metrics_count": null, "time_window": null, "product_id": null, "rating": null, "version": "2.1", "status": null, "test": null, "validation_errors": null}
{"timestamp": "2025-10-17T08:09:55.739954Z", "level": "INFO", "service": "notification-service", "host": "notif-server-01", "request_id": "req-d3c813ac", "message": "POST /api/v1/orders", "duration_ms": 267, "status_code": 204, "user_id": null, "amount": null, "error": null, "region": "ap-northeast-1", "trace_id": null, "auth_method": null, "provider": null, "session_duration": null, "currency": null, "payment_method": null, "retry_count": null, "file_size_bytes": null, "content_type": null, "memory_percent": null, "available_mb": null, "disk_usage_percent": null, "available_gb": null, "query_params": null, "result_count": null, "recipient": null, "smtp_code": null, "metrics_count": null, "time_window": null, "product_id": null, "rating": null, "version": null, "status": "degraded", "test": null, "validation_errors": null}
{"timestamp": "2025-10-17T08:09:55.739962Z", "level": "INFO", "service": "payment-service", "host": "payment-server-02", "request_id": "req-b36243eb", "message": "GET /api/v1/products", "duration_ms": 69, "status_code": 204, "user_id": null, "amount": 902.28, "error": null, "region": "us-central-1", "trace_id": null, "auth_method": null, "provider": null, "session_duration": null, "currency": "EUR", "payment_method": "paypal", "retry_count": null, "file_size_bytes": null, "content_type": null, "memory_percent": null, "available_mb": null, "disk_usage_percent": null, "available_gb": null, "query_params": null, "result_count": null, "recipient": null, "smtp_code": null, "metrics_count": null, "time_window": null, "product_id": null, "rating": null, "version": null, "status": null, "test": null, "validation_errors": null}
{"timestamp": "2025-10-17T08:09:55.739977Z", "level": "INFO", "service": "analytics-service", "host": "analytics-server-01", "request_id": "req-250a3f23", "message": "Search query executed", "duration_ms": 269, "status_code": 200, "user_id": "user-41948", "amount": null, "error": null, "region": "ap-south-1", "trace_id": "trace-8464f8a4e02eb756", "auth_method": null, "provider": null, "session_duration": null, "currency": null, "payment_method": null, "retry_count": null, "file_size_bytes": null, "content_type": null, "memory_percent": null, "available_mb": null, "disk_usage_percent": null, "available_gb": null, "query_params": null, "result_count": null, "recipient": null, "smtp_code": null, "metrics_count": null, "time_window": null, "product_id": null, "rating": null, "version": null, "status": null, "test": null, "validation_errors": null}
{"timestamp": "2025-10-17T08:09:55.739986Z", "level": "INFO", "service": "analytics-service", "host": "analytics-server-01", "request_id": "req-e9aaf90c", "message": "File uploaded successfully", "duration_ms": 135, "status_code": 201, "user_id": "user-97487", "amount": null, "error": null, "region": "us-central-1", "trace_id": null, "auth_method": null, "provider": null, "session_duration": null, "currency": null, "payment_method": null, "retry_count": null, "file_size_bytes": null, "content_type": null, "memory_percent": null, "available_mb": null, "disk_usage_percent": null, "available_gb": null, "query_params": null, "result_count": null, "recipient": null, "smtp_code": null, "metrics_count": null, "time_window": null, "product_id": null, "rating": null, "version": null, "status": null, "test": null, "validation_errors": null}
{"timestamp": "2025-10-17T08:09:55.739996Z", "level": "ERROR", "service": "analytics-service", "host": "analytics-server-01", "request_id": "req-7ec820af", "message": "Authentication failed", "duration_ms": 7902, "status_code": 500, "user_id": null, "amount": null, "error": "AuthenticationError", "region": "eu-west-1", "trace_id": null, "auth_method": null, "provider": null, "session_duration": null, "currency": null, "payment_method": null, "retry_count": 5, "file_size_bytes": null, "content_type": null, "memory_percent": null, "available_mb": null, "disk_usage_percent": null, "available_gb": null, "query_params": null, "result_count": null, "recipient": null, "smtp_code": null, "metrics_count": null, "time_window": null, "product_id": null, "rating": null, "version": null, "status": "degraded", "test": null, "validation_errors": null}
{"timestamp": "2025-10-17T08:09:55.740005Z", "level": "INFO", "service": "notification-service", "host": "notif-server-01", "request_id": "req-9abacefd", "message": "File uploaded successfully", "duration_ms": 113, "status_code": 201, "user_id": null, "amount": null, "error": null, "region": "us-east-1", "trace_id": "trace-9b70d4e90db24fa7", "auth_method": null, "provider": null, "session_duration": null, "currency": null, "payment_method": null, "retry_count": null, "file_size_bytes": null, "content_type": null, "memory_percent": null, "available_mb": null, "disk_usage_percent": null, "available_gb": null, "query_params": null, "result_count": null, "recipient": null, "smtp_code": null, "metrics_count": null, "time_window": null, "product_id": null, "rating": null, "version": null, "status": null, "test": null, "validation_errors": null}
{"timestamp": "2025-10-17T08:09:55.740013Z", "level": "INFO", "service": "search-service", "host": "search-server-01", "request_id": "req-1348a4a6", "message": "Payment processed", "duration_ms": 229, "status_code": 200, "user_id": "user-29739", "amount": null, "error": null, "region": "eu-west-1", "trace_id": null, "auth_method": null, "provider": null, "session_duration": null, "currency": null, "payment_method": null, "retry_count": null, "file_size_bytes": null, "content_type": null, "memory_percent": null, "available_mb": null, "disk_usage_percent": null, "available_gb": null, "query_params": null, "result_count": null, "recipient": null, "smtp_code": null, "metrics_count": null, "time_window": null, "product_id": null, "rating": null, "version": null, "status": null, "test": null, "validation_errors": null}
{"timestamp": "2025-10-17T08:09:55.740022Z", "level": "ERROR", "service": "search-service", "host": "search-server-01", "request_id": "req-d6637bfb", "message": "Database connection timeout", "duration_ms": 9727, "status_code": 409, "user_id": null, "amount": null, "error": "ConnectionTimeout", "region": "ap-south-1", "trace_id": null, "auth_method": null, "provider": null, "session_duration": null, "currency": null, "payment_method": null, "retry_count": 2, "file_size_bytes": null, "content_type": null, "memory_percent": null, "available_mb": null, "disk_usage_percent": null, "available_gb": null, "query_params": null, "result_count": null, "recipient": null, "smtp_code": null, "metrics_count": null, "time_window": null, "product_id": null, "rating": null, "version": null, "status": null, "test": null, "validation_errors": null}
{"timestamp": "2025-10-17T08:09:55.740071Z", "level": "ERROR", "service": "auth-service", "host": "auth-server-02", "request_id": "req-2b56b9b5", "message": "Invalid input data", "duration_ms": 6774, "status_code": 503, "user_id": null, "amount": null, "error": "ValidationError", "region": "ap-south-1", "trace_id": "trace-c174e5a51c8ff0cd", "auth_method": null, "provider": null, "session_duration": null, "currency": null, "payment_method": null, "retry_count": 4, "file_size_bytes": null, "content_type": null, "memory_percent": null, "available_mb": null, "disk_usage_percent": null, "available_gb": null, "query_params": null, "result_count": null, "recipient": null, "smtp_code": null, "metrics_count": null, "time_window": null, "product_id": null, "rating": null, "version": "1.5", "status": null, "test": null, "validation_errors": null}
{"timestamp": "2025-10-17T08:09:55.740100Z", "level": "INFO", "service": "web-api", "host": "api-server-02", "request_id": "req-e9aac280", "message": "Session created", "duration_ms": 462, "status_code": 204, "user_id": "user-54168", "amount": null, "error": null, "region": "eu-central-1", "trace_id": null, "auth_method": null, "provider": null, "session_duration": null, "currency": null, "payment_method": null, "retry_count": null, "file_size_bytes": null, "content_type": null, "memory_percent": null, "available_mb": null, "disk_usage_percent": null, "available_gb": null, "query_params": {"category": "electronics", "limit": 25}, "result_count": 0, "recipient": null, "smtp_code": null, "metrics_count": null, "time_window": null, "product_id": "prod-44964", "rating": 4, "version": null, "status": null, "test": null, "validation_errors": null}
{"timestamp": "2025-10-17T08:09:55.740117Z", "level": "INFO", "service": "notification-service", "host": "notif-server-01", "request_id": "req-d26a5ff4", "message": "Payment processed", "duration_ms": 233, "status_code": 201, "user_id": "user-94381", "amount": null, "error": null, "region": "ap-south-1", "trace_id": null, "auth_method": null, "provider": null, "session_duration": null, "currency": null, "payment_method": null, "retry_count": null, "file_size_bytes": null, "content_type": null, "memory_percent": null, "available_mb": null, "disk_usage_percent": null, "available_gb": null, "query_params": null, "result_count": null, "recipient": null, "smtp_code": null, "metrics_count": null, "time_window": null, "product_id": null, "rating": null, "version": null, "status": null, "test": null, "validation_errors": null}
{"timestamp": "2025-10-17T08:09:55.740127Z", "level": "INFO", "service": "inventory-service", "host": "inventory-server-01", "request_id": "req-70538f00", "message": "Payment processed", "duration_ms": 202, "status_code": 201, "user_id": "user-86516", "amount": null, "error": null, "region": "eu-west-1", "trace_id": "trace-f1c1815712a6fe32", "auth_method": null, "provider": null, "session_duration": null, "currency": null, "payment_method": null, "retry_count": null, "file_size_bytes": null, "content_type": null, "memory_percent": null, "available_mb": null, "disk_usage_percent": null, "available_gb": null, "query_params": null, "result_count": null, "recipient": null, "smtp_code": null, "metrics_count": null, "time_window": null, "product_id": null, "rating": null, "version": null, "status": null, "test": null, "validation_errors": null}
{"timestamp": "2025-10-17T08:09:55.740148Z", "level": "INFO", "service": "auth-service", "host": "auth-server-01", "request_id": "req-89f79000", "message": "Session created", "duration_ms": 304, "status_code": 204, "user_id": "user-41529", "amount": null, "error": null, "region": "us-west-2", "trace_id": null, "auth_method": "saml", "provider": "aws", "session_duration": 1800, "currency": null, "payment_method": null, "retry_count": null, "file_size_bytes": null, "content_type": null, "memory_percent": null, "available_mb": null, "disk_usage_percent": null, "available_gb": null, "query_params": null, "result_count": null, "recipient": null, "smtp_code": null, "metrics_count": null, "time_window": null, "product_id": null, "rating": null, "version": null, "status": null, "test": true, "validation_errors": null}
{"timestamp": "2025-10-17T08:09:55.740160Z", "level": "INFO", "service": "analytics-service", "host": "analytics-server-01", "request_id": "req-4a909c5f", "message": "Search query executed", "duration_ms": 331, "status_code": 201, "user_id": null, "amount": null, "error": null, "region": null, "trace_id": "trace-1824b29e413e3399", "auth_method": null, "provider": null, "session_duration": null, "currency": null, "payment_method": null, "retry_count": null, "file_size_bytes": null, "content_type": null, "memory_percent": null, "available_mb": null, "disk_usage_percent": null, "available_gb": null, "query_params": null, "result_count": null, "recipient": null, "smtp_code": null, "metrics_count": null, "time_window": null, "product_id": null, "rating": null, "version": null, "status": null, "test": null, "validation_errors": null}
{"timestamp": "2025-10-17T08:09:55.740169Z", "level": "INFO", "service": "payment-service", "host": "payment-server-01", "request_id": "req-a35f8537", "message": "User authentication successful", "duration_ms": 286, "status_code": 204, "user_id": null, "amount": null, "error": null, "region": "eu-central-1", "trace_id": null, "auth_method": null, "provider": null, "session_duration": null, "currency": null, "payment_method": null, "retry_count": null, "file_size_bytes": null, "content_type": null, "memory_percent": null, "available_mb": null, "disk_usage_percent": null, "available_gb": null, "query_params": null, "result_count": null, "recipient": null, "smtp_code": null, "metrics_count": null, "time_window": null, "product_id": null, "rating": null, "version": null, "status": null, "test": null, "validation_errors": null}
{"timestamp": "2025-10-17T08:09:55.740181Z", "level": "INFO", "service": "web-api", "host": "api-server-01", "request_id": "req-126db106", "message": "GET /api/v1/users/profile", "duration_ms": 469, "status_code": 201, "user_id": null, "amount": null, "error": null, "region": "us-central-1", "trace_id": null, "auth_method": null, "provider": null, "session_duration": null, "currency": null, "payment_method": null, "retry_count": null, "file_size_bytes": null, "content_type": null, "memory_percent": null, "available_mb": null, "disk_usage_percent": null, "available_gb": null, "query_params": null, "result_count": null, "recipient": null, "smtp_code": null, "metrics_count": null, "time_window": null, "product_id": null, "rating": null, "version": null, "status": null, "test": null, "validation_errors": null}
{"timestamp": "2025-10-17T08:09:55.740190Z", "level": "WARN", "service": "payment-service", "host": "payment-server-02", "request_id": "req-d064df2b", "message": "Disk space running low", "duration_ms": null, "status_code": 402, "user_id": null, "amount": 748.64, "error": null, "region": "ap-northeast-1", "trace_id": null, "auth_method": null, "provider": null, "session_duration": null, "currency": "USD", "payment_method": "debit_card", "retry_count": null, "file_size_bytes": null, "content_type": null, "memory_percent": null, "available_mb": null, "disk_usage_percent": 85, "available_gb": 13, "query_params": null, "result_count": null, "recipient": null, "smtp_code": null, "metrics_count": null, "time_window": null, "product_id": null, "rating": null, "version": null, "status": null, "test": null, "validation_errors": null}
{"timestamp": "2025-10-17T08:09:55.740215Z", "level": "INFO", "service": "payment-service", "host": "payment-server-02", "request_id": "req-662b9631", "message": "GET /api/v1/products", "duration_ms": 454, "status_code": 201, "user_id": "user-72118", "amount": 356.15, "error": null, "region": "eu-west-1", "trace_id": null, "auth_method": null, "provider": null, "session_duration": null, "currency": "GBP", "payment_method": "bank_transfer", "retry_count": null, "file_size_bytes": null, "content_type": null, "memory_percent": null, "available_mb": null, "disk_usage_percent": null, "available_gb": null, "query_params": null, "result_count": null, "recipient": null, "smtp_code": null, "metrics_count": null, "time_window": null, "product_id": null, "rating": null, "version": "2.1", "status": null, "test": null, "validation_errors": null}
{"timestamp": "2025-10-17T08:09:55.740227Z", "level": "INFO", "service": "db-service", "host": "db-server-01", "request_id": "req-e6270bc8", "message": "GET /api/v1/users/profile", "duration_ms": 208, "status_code": 200, "user_id": "user-79620", "amount": null, "error": null, "region": "eu-central-1", "trace_id": "trace-919114333a4a1732", "auth_method": null, "provider": null, "session_duration": null, "currency": null, "payment_method": null, "retry_count": null, "file_size_bytes": null, "content_type": null, "memory_percent": null, "available_mb": null, "disk_usage_percent": null, "available_gb": null, "query_params": null, "result_count": null, "recipient": null, "smtp_code": null, "metrics_count": null, "time_window": null, "product_id": null, "rating": null, "version": null, "status": null, "test": null, "validation_errors": null}
{"timestamp": "2025-10-17T08:09:55.740237Z", "level": "INFO", "service": "db-service", "host": "db-server-01", "request_id": "req-3a2a6aa5", "message": "DELETE /api/v1/cart/items", "duration_ms": 421, "status_code": 200, "user_id": "user-10503", "amount": null, "error": null, "region": "us-east-1", "trace_id": null, "auth_method": null, "provider": null, "session_duration": null, "currency": null, "payment_method": null, "retry_count": null, "file_size_bytes": null, "content_type": null, "memory_percent": null, "available_mb": null, "disk_usage_percent": null, "available_gb": null, "query_params": null, "result_count": null, "recipient": null, "smtp_code": null, "metrics_count": null, "time_window": null, "product_id": null, "rating": null, "version": null, "status": null, "test": null, "validation_errors": null}
{"timestamp": "2025-10-17T08:09:55.740246Z", "level": "WARN", "service": "search-service", "host": "search-server-02", "request_id": "req-b5eb6f34", "message": "Disk space running low", "duration_ms": 1343, "status_code": 402, "user_id": "user-15963", "amount": null, "error": null, "region": "us-west-2", "trace_id": "trace-add8afec7510629a", "auth_method": null, "provider": null, "session_duration": null, "currency": null, "payment_method": null, "retry_count": null, "file_size_bytes": null, "content_type": null, "memory_percent": null, "available_mb": null, "disk_usage_percent": 94, "available_gb": 12, "query_params": null, "result_count": null, "recipient": null, "smtp_code": null, "metrics_count": null, "time_window": null, "product_id": null, "rating": null, "version": "2.0", "status": null, "test": null, "validation_errors": null}
{"timestamp": "2025-10-17T08:09:55.740257Z", "level": "INFO", "service": "search-service", "host": "search-server-02", "request_id": "req-ea39c7a6", "message": "SMS notification sent", "duration_ms": 457, "status_code": 200, "user_id": "user-43106", "amount": null, "error": null, "region": "eu-west-1", "trace_id": null, "auth_method": null, "provider": null, "session_duration": null, "currency": null, "payment_method": null, "retry_count": null, "file_size_bytes": null, "content_type": null, "memory_percent": null, "available_mb": null, "disk_usage_percent": null, "available_gb": null, "query_params": null, "result_count": null, "recipient": null, "smtp_code": null, "metrics_count": null, "time_window": null, "product_id": null, "rating": null, "version": null, "status": null, "test": null, "validation_errors": null}
{"timestamp": "2025-10-17T08:09:55.740273Z", "level": "INFO", "service": "search-service", "host": "search-server-01", "request_id": "req-0e2efaa7", "message": "GET /api/v1/users/profile", "duration_ms": 445, "status_code": 204, "user_id": "user-13827", "amount": null, "error": null, "region": null, "trace_id": null, "auth_method": null, "provider": null, "session_duration": null, "currency": null, "payment_method": null, "retry_count": null, "file_size_bytes": null, "content_type": null, "memory_percent": null, "available_mb": null, "disk_usage_percent": null, "available_gb": null, "query_params": null, "result_count": null, "recipient": null, "smtp_code": null, "metrics_count": null, "time_window": null, "product_id": null, "rating": null, "version": null, "status": null, "test": null, "validation_errors": null}
{"timestamp": "2025-10-17T08:09:55.740282Z", "level": "WARN", "service": "auth-service", "host": "auth-server-01", "request_id": "req-f497b5bb", "message": "Disk space running low", "duration_ms": 1022, "status_code": 200, "user_id": null, "amount": null, "error": null, "region": null, "trace_id": "trace-8e3863d6623558de", "auth_method": null, "provider": null, "session_duration": null, "currency": null, "payment_method": null, "retry_count": null, "file_size_bytes": null, "content_type": null, "memory_percent": null, "available_mb": null, "disk_usage_percent": 95, "available_gb": 39, "query_params": null, "result_count": null, "recipient": null, "smtp_code": null, "metrics_count": null, "time_window": null, "product_id": null, "rating": null, "version": null, "status": null, "test": null, "validation_errors": null}
{"timestamp": "2025-10-17T08:09:55.740292Z", "level": "INFO", "service": "db-service", "host": "db-server-01", "request_id": "req-0a7f2c26", "message": "Request processed successfully", "duration_ms": 440, "status_code": 201, "user_id": "user-38217", "amount": null, "error": null, "region": null, "trace_id": null, "auth_method": null, "provider": null, "session_duration": null, "currency": null, "payment_method": null, "retry_count": null, "file_size_bytes": null, "content_type": null, "memory_percent": null, "available_mb": null, "disk_usage_percent": null, "available_gb": null, "query_params": null, "result_count": null, "recipient": null, "smtp_code": null, "metrics_count": null, "time_window": null, "product_id": null, "rating": null, "version": null, "status": null, "test": null, "validation_errors": null}
{"timestamp": "2025-10-17T08:09:55.740299Z", "level": "ERROR", "service": "notification-service", "host": "notif-server-01", "request_id": "req-85dd9f52", "message": "Internal server error", "duration_ms": 8845, "status_code": 500, "user_id": null, "amount": null, "error": "NullPointerException", "region": "us-central-1", "trace_id": "trace-0c1e747b63ca8193", "auth_method": null, "provider": null, "session_duration": null, "currency": null, "payment_method": null, "retry_count": 3, "file_size_bytes": null, "content_type": null, "memory_percent": null, "available_mb": null, "disk_usage_percent": null, "available_gb": null, "query_params": null, "result_count": null, "recipient": "user7574@example.com", "smtp_code": 421, "metrics_count": null, "time_window": null, "product_id": null, "rating": null, "version": null, "status": null, "test": null, "validation_errors": null}
{"timestamp": "2025-10-17T08:09:55.740324Z", "level": "WARN", "service": "notification-service", "host": "notif-server-01", "request_id": "req-e578695e", "message": "Connection pool nearly exhausted", "duration_ms": 1735, "status_code": 200, "user_id": "user-20366", "amount": null, "error": null, "region": null, "trace_id": null, "auth_method": null, "provider": null, "session_duration": null, "currency": null, "payment_method": null, "retry_count": null, "file_size_bytes": null, "content_type": null, "memory_percent": null, "available_mb": null, "disk_usage_percent": null, "available_gb": null, "query_params": null, "result_count": null, "recipient": null, "smtp_code": null, "metrics_count": null, "time_window": null, "product_id": null, "rating": null, "version": null, "status": null, "test": null, "validation_errors": null}
{"timestamp": "2025-10-17T08:09:55.740333Z", "level": "WARN", "service": "auth-service", "host": "auth-server-02", "request_id": "req-de2b800c", "message": "Query execution took longer than expected", "duration_ms": null, "status_code": 200, "user_id": "user-22758", "amount": null, "error": null, "region": "eu-central-1", "trace_id": null, "auth_method": null, "provider": null, "session_duration": null, "currency": null, "payment_method": null, "retry_count": null, "file_size_bytes": null, "content_type": null, "memory_percent": null, "available_mb": null, "disk_usage_percent": null, "available_gb": null, "query_params": null, "result_count": null, "recipient": null, "smtp_code": null, "metrics_count": null, "time_window": null, "product_id": null, "rating": null, "version": null, "status": null, "test": null, "validation_errors": null}
{"timestamp": "2025-10-17T08:09:55.740341Z", "level": "WARN", "service": "auth-service", "host": "auth-server-01", "request_id": "req-0609652c", "message": "Query execution took longer than expected", "duration_ms": 831, "status_code": 200, "user_id": "user-22655", "amount": null, "error": null, "region": "ap-south-1", "trace_id": "trace-ddc36cac99c00f65", "auth_method": null, "provider": null, "session_duration": null, "currency": null, "payment_method": null, "retry_count": null, "file_size_bytes": null, "content_type": null, "memory_percent": null, "available_mb": null, "disk_usage_percent": null, "available_gb": null, "query_params": null, "result_count": null, "recipient": null, "smtp_code": null, "metrics_count": null, "time_window": null, "product_id": null, "rating": null, "version": null, "status": null, "test": null, "validation_errors": null}
{"timestamp": "2025-10-17T08:09:55.740350Z", "level": "ERROR", "service": "web-api", "host": "api-server-03", "request_id": "req-dc00ec22", "message": "Database connection timeout", "duration_ms": 1428, "status_code": 500, "user_id": null, "amount": null, "error": "ConnectionTimeout", "region": "ap-northeast-1", "trace_id": null, "auth_method": null, "provider": null, "session_duration": null, "currency": null, "payment_method": null, "retry_count": 1, "file_size_bytes": null, "content_type": null, "memory_percent": null, "available_mb": null, "disk_usage_percent": null, "available_gb": null, "query_params": null, "result_count": null, "recipient": null, "smtp_code": null, "metrics_count": null, "time_window": null, "product_id": null, "rating": null, "version": null, "status": null, "test": null, "validation_errors": null}
{"timestamp": "2025-10-17T08:09:55.740359Z", "level": "INFO", "service": "notification-service", "host": "notif-server-01", "request_id": "req-ccc86922", "message": "POST /api/v1/orders", "duration_ms": 205, "status_code": 201, "user_id": "user-56684", "amount": null, "error": null, "region": "us-west-2", "trace_id": "trace-a8a0a1d6a88940bf", "auth_method": null, "provider": null, "session_duration": null, "currency": null, "payment_method": null, "retry_count": null, "file_size_bytes": null, "content_type": null, "memory_percent": null, "available_mb": null, "disk_usage_percent": null, "available_gb": null, "query_params": null, "result_count": null, "recipient": null, "smtp_code": null, "metrics_count": null, "time_window": null, "product_id": null, "rating": null, "version": null, "status": null, "test": null, "validation_errors": null}
{"timestamp": "2025-10-17T08:09:55.740367Z", "level": "INFO", "service": "auth-service", "host": "auth-server-02", "request_id": "req-5a38dcfd", "message": "SMS notification sent", "duration_ms": 151, "status_code": 204, "user_id": "user-73791", "amount": null, "error": null, "region": "eu-west-1", "trace_id": "trace-71126d014b8069f0", "auth_method": "basic", "provider": "google", "session_duration": null, "currency": null, "payment_method": null, "retry_count": null, "file_size_bytes": null, "content_type": null, "memory_percent": null, "available_mb": null, "disk_usage_percent": null, "available_gb": null, "query_params": null, "result_count": null, "recipient": null, "smtp_code": null, "metrics_count": null, "time_window": null, "product_id": null, "rating": null, "version": null, "status": null, "test": null, "validation_errors": null}
{"timestamp": "2025-10-17T08:09:55.740383Z", "level": "INFO", "service": "web-api", "host": "api-server-01", "request_id": "req-350d1f7e", "message": "Payment processed", "duration_ms": 440, "status_code": 200, "user_id": null, "amount": null, "error": null, "region": "ap-northeast-1", "trace_id": null, "auth_method": null, "provider": null, "session_duration": null, "currency": null, "payment_method": null, "retry_count": null, "file_size_bytes": null, "content_type": null, "memory_percent": null, "available_mb": null, "disk_usage_percent": null, "available_gb": null, "query_params": {"category": "electronics", "limit": 10}, "result_count": 3, "recipient": null, "smtp_code": null, "metrics_count": null, "time_window": null, "product_id": "prod-79965", "rating": 1, "version": null, "status": null, "test": null, "validation_errors": null}
{"timestamp": "2025-10-17T08:09:55.740425Z", "level": "INFO", "service": "web-api", "host": "api-server-01", "request_id": "req-74b833c2", "message": "PUT /api/v1/cart", "duration_ms": 377, "status_code": 201, "user_id": null, "amount": null, "error": null, "region": "us-east-1", "trace_id": "trace-bb65a65178a49329", "auth_method": null, "provider": null, "session_duration": null, "currency": null, "payment_method": null, "retry_count": null, "file_size_bytes": null, "content_type": null, "memory_percent": null, "available_mb": null, "disk_usage_percent": null, "available_gb": null, "query_params": {"category": "books", "limit": 100}, "result_count": 74, "recipient": null, "smtp_code": null, "metrics_count": null, "time_window": null, "product_id": "prod-35780", "rating": 2, "version": null, "status": null, "test": null, "validation_errors": null}
{"timestamp": "2025-10-17T08:09:55.740457Z", "level": "INFO", "service": "auth-service", "host": "auth-server-01", "request_id": "req-ec153885", "message": "User authentication successful", "duration_ms": 298, "status_code": 200, "user_id": "user-96910", "amount": null, "error": null, "region": "eu-west-1", "trace_id": null, "auth_method": "basic", "provider": "okta", "session_duration": null, "currency": null, "payment_method": null, "retry_count": null, "file_size_bytes": null, "content_type": null, "memory_percent": null, "available_mb": null, "disk_usage_percent": null, "available_gb": null, "query_params": null, "result_count": null, "recipient": null, "smtp_code": null, "metrics_count": null, "time_window": null, "product_id": null, "rating": null, "version": null, "status": null, "test": null, "validation_errors": null}
{"timestamp": "2025-10-17T08:09:55.740509Z", "level": "INFO", "service": "analytics-service", "host": "analytics-server-01", "request_id": "req-8c0f019b", "message": "Search query executed", "duration_ms": 395, "status_code": 201, "user_id": null, "amount": null, "error": null, "region": null, "trace_id": null, "auth_method": null, "provider": null, "session_duration": null, "currency": null, "payment_method": null, "retry_count": null, "file_size_bytes": null, "content_type": null, "memory_percent": null, "available_mb": null, "disk_usage_percent": null, "available_gb": null, "query_params": null, "result_count": null, "recipient": null, "smtp_code": null, "metrics_count": null, "time_window": null, "product_id": null, "rating": null, "version": null, "status": null, "test": null, "validation_errors": null}
{"timestamp": "2025-10-17T08:09:55.740521Z", "level": "WARN", "service": "inventory-service", "host": "inventory-server-02", "request_id": "req-038b3467", "message": "Query execution took longer than expected", "duration_ms": null, "status_code": 402, "user_id": "user-12820", "amount": null, "error": null, "region": null, "trace_id": null, "auth_method": null, "provider": null, "session_duration": null, "currency": null, "payment_method": null, "retry_count": null, "file_size_bytes": null, "content_type": null, "memory_percent": null, "available_mb": null, "disk_usage_percent": null, "available_gb": null, "query_params": null, "result_count": null, "recipient": null, "smtp_code": null, "metrics_count": null, "time_window": null, "product_id": null, "rating": null, "version": "1.0", "status": null, "test": null, "validation_errors": null}
{"timestamp": "2025-10-17T08:09:55.740530Z", "level": "INFO", "service": "analytics-service", "host": "analytics-server-01", "request_id": "req-dba50b89", "message": "Daily report generated", "duration_ms": 131, "status_code": 204, "user_id": null, "amount": null, "error": null, "region": "us-west-2", "trace_id": "trace-3d050c628da3b0a1", "auth_method": null, "provider": null, "session_duration": null, "currency": null, "payment_method": null, "retry_count": null, "file_size_bytes": null, "content_type": null, "memory_percent": null, "available_mb": null, "disk_usage_percent": null, "available_gb": null, "query_params": null, "result_count": null, "recipient": null, "smtp_code": null, "metrics_count": null, "time_window": null, "product_id": null, "rating": null, "version": null, "status": null, "test": null, "validation_errors": null}
{"timestamp": "2025-10-17T08:09:55.740539Z", "level": "INFO", "service": "notification-service", "host": "notif-server-01", "request_id": "req-91ebfa4c", "message": "PUT /api/v1/cart", "duration_ms": 304, "status_code": 200, "user_id": "user-37774", "amount": null, "error": null, "region": "us-west-2", "trace_id": null, "auth_method": null, "provider": null, "session_duration": null, "currency": null, "payment_method": null, "retry_count": null, "file_size_bytes": null, "content_type": null, "memory_percent": null, "available_mb": null, "disk_usage_percent": null, "available_gb": null, "query_params": null, "result_count": null, "recipient": null, "smtp_code": null, "metrics_count": null, "time_window": null, "product_id": null, "rating": null, "version": null, "status": "unhealthy", "test": null, "validation_errors": null}
{"timestamp": "2025-10-17T08:09:55.740546Z", "level": "INFO", "service": "inventory-service", "host": "inventory-server-02", "request_id": "req-cb2d72be", "message": "PUT /api/v1/cart", "duration_ms": 464, "status_code": 201, "user_id": "user-23852", "amount": null, "error": null, "region": "us-west-2", "trace_id": null, "auth_method": null, "provider": null, "session_duration": null, "currency": null, "payment_method": null, "retry_count": null, "file_size_bytes": null, "content_type": null, "memory_percent": null, "available_mb": null, "disk_usage_percent": null, "available_gb": null, "query_params": null, "result_count": null, "recipient": null, "smtp_code": null, "metrics_count": null, "time_window": null, "product_id": null, "rating": null, "version": null, "status": null, "test": null, "validation_errors": null}
{"timestamp": "2025-10-17T08:09:55.740554Z", "level": "INFO", "service": "web-api", "host": "api-server-03", "request_id": "req-394652ed", "message": "Search query executed", "duration_ms": 468, "status_code": 204, "user_id": null, "amount": null, "error": null, "region": "us-west-2", "trace_id": "trace-3e7ec0e0f072f27b", "auth_method": null, "provider": null, "session_duration": null, "currency": null, "payment_method": null, "retry_count": null, "file_size_bytes": 6168077, "content_type": "image/jpeg", "memory_percent": null, "available_mb": null, "disk_usage_percent": null, "available_gb": null, "query_params": null, "result_count": null, "recipient": null, "smtp_code": null, "metrics_count": null, "time_window": null, "product_id": null, "rating": null, "version": null, "status": null, "test": null, "validation_errors": null}
{"timestamp": "2025-10-17T08:09:55.740564Z", "level": "ERROR", "service": "db-service", "host": "db-server-01", "request_id": "req-0357b04a", "message": "Internal server error", "duration_ms": 4535, "status_code": 500, "user_id": null, "amount": null, "error": "NullPointerException", "region": null, "trace_id": null, "auth_method": null, "provider": null, "session_duration": null, "currency": null, "payment_method": null, "retry_count": null, "file_size_bytes": null, "content_type": null, "memory_percent": null, "available_mb": null, "disk_usage_percent": null, "available_gb": null, "query_params": null, "result_count": null, "recipient": null, "smtp_code": null, "metrics_count": null, "time_window": null, "product_id": null, "rating": null, "version": null, "status": null, "test": null, "validation_errors": null}
